[
  {
    "_id": "ITEM001",
    "restaurantId": 101,
    "categoryId": "CAT001",
    "name": "Veg Hakka Noodles",
    "description": "Stir-fried noodles with seasonal vegetables",
    "basePrice": 160,
    "veg": true,
    "enabled": true,
    "variants": [
      {
        "id": "VAR001",
        "label": "Half",
        "price": 99,
        "available": true
      },
      {
        "id": "VAR002",
        "label": "Full",
        "price": 160,
        "available": true
      }
    ],
    "addons": [
      {
        "id": "ADD001",
        "name": "Extra Sauce",
        "price": 20,
        "available": true
      }
    ]
  },
  {
    "_id": "ITEM002",
    "restaurantId": 101,
    "categoryId": "CAT001",
    "name": "Chicken Manchurian",
    "description": "Crispy chicken tossed in spicy Manchurian sauce",
    "basePrice": 220,
    "veg": false,
    "enabled": true,
    "variants": [
      {
        "id": "VAR003",
        "label": "Dry",
        "price": 220,
        "available": true
      },
      {
        "id": "VAR004",
        "label": "Gravy",
        "price": 230,
        "available": true
      }
    ],
    "addons": [
      {
        "id": "ADD002",
        "name": "Extra Gravy",
        "price": 25,
        "available": true
      }
    ]
  },
  {
    "_id": "ITEM003",
    "restaurantId": 101,
    "categoryId": "CAT002",
    "name": "Paneer Biryani",
    "description": "Spiced paneer layered with basmati rice",
    "basePrice": 199,
    "veg": true,
    "enabled": true,
    "variants": [],
    "addons": [
      {
        "id": "ADD003",
        "name": "Raita",
        "price": 20,
        "available": true
      }
    ]
  },
  {
    "_id": "ITEM004",
    "restaurantId": 101,
    "categoryId": "CAT003",
    "name": "Fresh Lime Soda",
    "description": "Sweet or salted — your choice",
    "basePrice": 69,
    "veg": true,
    "enabled": true,
    "variants": [],
    "addons": []
  }
]